clean_text_rhoni/__init__.py
clean_text_rhoni/base_clean_text.py
clean_text_rhoni/clean_text_rhoni.py
clean_text_rhoni-0.1.14.dist-info/LICENSE
clean_text_rhoni-0.1.14.dist-info/METADATA
clean_text_rhoni-0.1.14.dist-info/WHEEL
clean_text_rhoni-0.1.14.dist-info/RECORD
