Metadata-Version: 2.1
Name: clean_text_rhoni
Version: 0.1.14
Summary: package to clean and normalize text
Home-page: https://github.com/rhoni-team/clean_text_rhoni
License: MIT
Author: rhoni
Requires-Python: >=3.8
Classifier: License :: OSI Approved :: MIT License
Classifier: Programming Language :: Python :: 3
Classifier: Programming Language :: Python :: 3.8
Classifier: Programming Language :: Python :: 3.9
Classifier: Programming Language :: Python :: 3.10
Classifier: Programming Language :: Python :: 3.11
Classifier: Programming Language :: Python :: 3.12
Project-URL: Documentation, https://clean-text-rhoni.readthedocs.io/en/latest/
Project-URL: Repository, https://github.com/rhoni-team/clean_text_rhoni
